mpcutilities/__init__.py
mpcutilities/classes.py
mpcutilities/ele220.py
mpcutilities/helloworld.py
mpcutilities/kepcart.py
mpcutilities/leapsec.py
mpcutilities/mpcutilities.py
mpcutilities/obs80.py
mpcutilities/obs80_clip.py
mpcutilities/obscode.py
mpcutilities/phys_const.py
mpcutilities/scan_obs80.py
mpcutilities-0.1.4.dist-info/AUTHORS.rst
mpcutilities-0.1.4.dist-info/LICENSE
mpcutilities-0.1.4.dist-info/METADATA
mpcutilities-0.1.4.dist-info/WHEEL
mpcutilities-0.1.4.dist-info/top_level.txt
mpcutilities-0.1.4.dist-info/RECORD
