Metadata-Version: 2.1
Name: mpcutilities
Version: 0.1.4
Summary: MPC Utilities contains standard, cross-package MPC Functionalities
Home-page: https://github.com/matthewjohnpayne/mpcutilities
Author: Matthew John Payne
Author-email: matthewjohnpayne@gmail.com
License: MIT license
Keywords: mpcutilities
Platform: UNKNOWN
Classifier: Development Status :: 2 - Pre-Alpha
Classifier: Intended Audience :: Developers
Classifier: License :: OSI Approved :: MIT License
Classifier: Natural Language :: English
Classifier: Programming Language :: Python :: 2
Classifier: Programming Language :: Python :: 2.7
Classifier: Programming Language :: Python :: 3
Classifier: Programming Language :: Python :: 3.4
Classifier: Programming Language :: Python :: 3.5
Classifier: Programming Language :: Python :: 3.6
Requires-Dist: numpy
Requires-Dist: novas
Requires-Dist: novas-de405
Requires-Dist: astropy
Requires-Dist: scipy
